hping/__init__.py
hping/__main__.py
hping/client.py
hping/headers.py
hping/main.py
hping/stats.py
hping-0.7.0.dist-info/METADATA
hping-0.7.0.dist-info/WHEEL
hping-0.7.0.dist-info/entry_points.txt
hping-0.7.0.dist-info/RECORD
