Metadata-Version: 2.4
Name: hping
Version: 0.7.0
Summary: A simple CLI tool to ping HTTP servers
License: MIT
Author: Lukas Holzner
Author-email: git@lukas.lhal.de
Requires-Python: >=3.10,<4.0
Classifier: License :: OSI Approved :: MIT License
Classifier: Programming Language :: Python :: 3
Classifier: Programming Language :: Python :: 3.10
Classifier: Programming Language :: Python :: 3.11
Classifier: Programming Language :: Python :: 3.12
Classifier: Programming Language :: Python :: 3.13
Classifier: Programming Language :: Python :: 3.14
Requires-Dist: httpx[http2] (>=0.28,<0.29)
